botsociety/__init__.py
botsociety/version.py
botsociety_client-1.1.0.dist-info/METADATA
botsociety_client-1.1.0.dist-info/RECORD
botsociety_client-1.1.0.dist-info/WHEEL
botsociety_client-1.1.0.dist-info/top_level.txt
