Metadata-Version: 2.1
Name: botsociety-client
Version: 1.1.0
Summary: Client to connect to Botsociety
Home-page: https://rasa.com
Author: Rasa Technologies GmbH
Author-email: hi@rasa.com
Maintainer: Tom Bocklisch
Maintainer-email: tom@rasa.com
License: Apache 2.0
Download-URL: https://github.com/RasaHQ/botsociety-py-client/archive/1.1.0.tar.gz
Project-URL: Source, https://github.com/RasaHQ/botsociety-py-client
Project-URL: Bug Reports, https://github.com/RasaHQ/botsociety-py-client/issues
Keywords: botsociety,bots,dialogue
Platform: UNKNOWN
Classifier: Development Status :: 4 - Beta
Classifier: Intended Audience :: Developers
Classifier: License :: OSI Approved :: Apache Software License
Classifier: Programming Language :: Python
Classifier: Programming Language :: Python :: 2.7
Classifier: Programming Language :: Python :: 3.5
Classifier: Programming Language :: Python :: 3.6
Classifier: Topic :: Software Development :: Libraries
Requires-Dist: requests
